[
	{"type": "Knight", "speed": 2, "power": 3, "defens": 3, "maxhp":100, "inventory1" : "new tool ('Sword', 'Weapon', 10, false, 'grey')", "inventory2" : "new tool ('sheild', 'Armor', 5, false, 'grey')", "inventory3" : "new tool ('armor', 'Armor', 6, false, 'grey')", "xcolnum" : 0, "ycolnum" : 0},
	{"type": "Wizard", "speed": 3, "power": 2, "defens": 2, "maxhp":75, "inventory1":"new tool ('staff', 'Weapon', 7, false, 'grey')", "inventory2":"new tool ('spell book', 'Magic', false, false, 'grey')", "inventory3":"new tool ('cloak', 'Armor', 4, false, 'grey')", "xcolnum" : 0, "ycolnum" : 1},
	{"type": "Rogue", "speed": 4, "power": 2, "defens": 1, "maxhp":50, "inventory1":"new tool ('dagger', 'Weapon', 3, false, 'grey')", "inventory2":"new tool ('dagger', 'Weapon', 3, false, 'grey')", "inventory3":"new tool ('cloak', 'Armor', 1, false, 'black')", "xcolnum" : 0, "ycolnum" : 2}
]